liveboot/cli.py
liveboot/cli2.py
liveboot/idrac.py
liveboot/test_iso.py
liveboot/version.py
liveboot/waitloop.py
liveboot/templates/cloud-init-template.yaml.j2
liveboot-0.0.4.data/scripts/build-rpm-liveboot.sh
liveboot-0.0.4.data/scripts/patch-ubuntu-image.sh
liveboot-0.0.4.data/scripts/seed-cloud-init.sh
liveboot-0.0.4.dist-info/METADATA
liveboot-0.0.4.dist-info/WHEEL
liveboot-0.0.4.dist-info/entry_points.txt
liveboot-0.0.4.dist-info/top_level.txt
liveboot-0.0.4.dist-info/RECORD
