Metadata-Version: 2.1
Name: liveboot
Version: 0.0.4
Summary: Testbed Management Framework for Sophia Node
Author: Thierry Parmentelat
Author-email: thierry.parmentelat@inria.fr
License: CC BY-SA 4.0
Project-URL: source, https://github.com/sopnode/liveboot/
Keywords: Sophia Node,networking testbed
Classifier: Development Status :: 4 - Beta
Classifier: Environment :: Console
Classifier: Intended Audience :: Information Technology
Classifier: Programming Language :: Python :: 3.10
Requires-Python: >=3.10
Requires-Dist: redfish
Requires-Dist: PyYAML
Requires-Dist: jmespath
Requires-Dist: jinja2
Requires-Dist: jinja2-cli[yaml]
Requires-Dist: requests
